LICENSE
MANIFEST.in
README.rst
setup.cfg
setup.py
src/pkdb_data/__init__.py
src/pkdb_data/_manipulation.py
src/pkdb_data/py.typed
src/pkdb_data.egg-info/PKG-INFO
src/pkdb_data.egg-info/SOURCES.txt
src/pkdb_data.egg-info/dependency_links.txt
src/pkdb_data.egg-info/entry_points.txt
src/pkdb_data.egg-info/requires.txt
src/pkdb_data.egg-info/top_level.txt
src/pkdb_data.egg-info/zip-safe
src/pkdb_data/info_nodes/__init__.py
src/pkdb_data/info_nodes/annotation.py
src/pkdb_data/info_nodes/node.py
src/pkdb_data/info_nodes/nodes.py
src/pkdb_data/info_nodes/units.py
src/pkdb_data/info_nodes/definitions/__init__.py
src/pkdb_data/info_nodes/definitions/anthropometry.py
src/pkdb_data/info_nodes/definitions/calculation_type.py
src/pkdb_data/info_nodes/definitions/demographics.py
src/pkdb_data/info_nodes/definitions/disease.py
src/pkdb_data/info_nodes/definitions/dosing.py
src/pkdb_data/info_nodes/definitions/ethnicity.py
src/pkdb_data/info_nodes/definitions/genetics.py
src/pkdb_data/info_nodes/definitions/imaging.py
src/pkdb_data/info_nodes/definitions/lifestyle.py
src/pkdb_data/info_nodes/definitions/measurement.py
src/pkdb_data/info_nodes/definitions/medical_procedure.py
src/pkdb_data/info_nodes/definitions/method.py
src/pkdb_data/info_nodes/definitions/specie.py
src/pkdb_data/info_nodes/definitions/substance.py
src/pkdb_data/info_nodes/definitions/tissue.py
src/pkdb_data/info_nodes/network/__init__.py
src/pkdb_data/info_nodes/network/pkdb_network.py
src/pkdb_data/management/__init__.py
src/pkdb_data/management/api.py
src/pkdb_data/management/commands.py
src/pkdb_data/management/envs.py
src/pkdb_data/management/index.py
src/pkdb_data/management/manage.py
src/pkdb_data/management/query.py
src/pkdb_data/management/reference.py
src/pkdb_data/management/tsv.py
src/pkdb_data/management/upload_studies.py
src/pkdb_data/management/users.py
src/pkdb_data/management/utils.py
src/pkdb_data/resources/cache/unichem_sources.json
src/pkdb_data/resources/cache/chebi/CHEBI%3A10023.json
src/pkdb_data/resources/cache/chebi/CHEBI%3A100241.json
src/pkdb_data/resources/cache/chebi/CHEBI%3A100246.json
src/pkdb_data/resources/cache/chebi/CHEBI%3A10033.json
src/pkdb_data/resources/cache/chebi/CHEBI%3A10125.json
