Metadata-Version: 2.1
Name: pkdb_data
Version: 1.0.9
Summary: PK-DB data utilities.
Home-page: https://github.com/matthiaskoenig/pkdb_data
Download-URL: https://pypi.org/project/pkdb_data
Author: Matthias König and Jan Grzegorzewski
Author-email: konigmatt@googlemail.com
Maintainer: Matthias Koenig
Maintainer-email: konigmatt@googlemail.com
License: LGPL-3.0
Project-URL: Source Code, https://github.com/matthiaskoenig/pkdb_data
Project-URL: Documentation, https://github.com/matthiaskoenig/pkdb_data
Project-URL: Bug Tracker, https://github.com/matthiaskoenig/pkdb_data/issues
Keywords: pharmacokinetics,pbpk
Classifier: Development Status :: 4 - Beta
Classifier: Intended Audience :: Science/Research
Classifier: License :: OSI Approved :: GNU Lesser General Public License v3 (LGPLv3)
Classifier: Operating System :: OS Independent
Classifier: Programming Language :: Python :: 3.9
Classifier: Programming Language :: Python :: 3.10
Classifier: Programming Language :: Python :: 3.11
Classifier: Programming Language :: Python :: 3.12
Classifier: Programming Language :: Python :: Implementation :: CPython
Classifier: Topic :: Scientific/Engineering
Classifier: Topic :: Scientific/Engineering :: Bio-Informatics
Requires-Python: >=3.9
License-File: LICENSE
Requires-Dist: pymetadata>=0.3.11
Requires-Dist: rich>=12.6
Requires-Dist: requests>=2.28
Requires-Dist: numpy>=1.21.3
Requires-Dist: pandas>=1.5
Requires-Dist: pint>=0.19.2
Requires-Dist: openpyxl>=3.0.10
Requires-Dist: python-slugify>=7.0.0
Requires-Dist: biopython>=1.80
Provides-Extra: development
Requires-Dist: pip-tools>6.10; extra == "development"
Requires-Dist: black>=24.1.1; extra == "development"
Requires-Dist: bump2version>=1.0.1; extra == "development"
Requires-Dist: isort>=5.13.2; extra == "development"
Requires-Dist: tox>=4.12.1; extra == "development"
Requires-Dist: flake8>=6.1.0; extra == "development"
Requires-Dist: flake8-mypy>=17.8.0; extra == "development"
Requires-Dist: mypy>=1.8.0; extra == "development"
Requires-Dist: pytest>=8.0.0; extra == "development"
Requires-Dist: pytest-cov>=4.1.0; extra == "development"
